[
    {
        "DateTime": "2025-03-20T23:00:00Z",
        "PriceInEUR": 0.019510000000000003,
        "PriceInEURIncludingVAT": 0.024387500000000003,
        "VATRate": 0.25,
        "PriceInLocalCurrency": 0.21467869718309862,
        "PriceInLocalCurrencyIncludingVAT": 0.26834837147887325,
        "ExchangeRate": 0.09088,
        "Currency": "SEK"
    },
    {
        "DateTime": "2025-03-21T00:00:00Z",
        "PriceInEUR": 0.022510000000000002,
        "PriceInEURIncludingVAT": 0.028137500000000003,
        "VATRate": 0.25,
        "PriceInLocalCurrency": 0.2476892605633803,
        "PriceInLocalCurrencyIncludingVAT": 0.3096115757042254,
        "ExchangeRate": 0.09088,
        "Currency": "SEK"
    },
    {
        "DateTime": "2025-03-21T01:00:00Z",
        "PriceInEUR": 0.02557,
        "PriceInEURIncludingVAT": 0.0319625,
        "VATRate": 0.25,
        "PriceInLocalCurrency": 0.28136003521126757,
        "PriceInLocalCurrencyIncludingVAT": 0.3517000440140845,
        "ExchangeRate": 0.09088,
        "Currency": "SEK"
    },
    {
        "DateTime": "2025-03-21T02:00:00Z",
        "PriceInEUR": 0.02683,
        "PriceInEURIncludingVAT": 0.0335375,
        "VATRate": 0.25,
        "PriceInLocalCurrency": 0.2952244718309859,
        "PriceInLocalCurrencyIncludingVAT": 0.3690305897887324,
        "ExchangeRate": 0.09088,
        "Currency": "SEK"
    },
    {
        "DateTime": "2025-03-21T03:00:00Z",
        "PriceInEUR": 0.03111,
        "PriceInEURIncludingVAT": 0.0388875,
        "VATRate": 0.25,
        "PriceInLocalCurrency": 0.3423195422535211,
        "PriceInLocalCurrencyIncludingVAT": 0.4278994278169014,
        "ExchangeRate": 0.09088,
        "Currency": "SEK"
    },
    {
        "DateTime": "2025-03-21T04:00:00Z",
        "PriceInEUR": 0.02729,
        "PriceInEURIncludingVAT": 0.0341125,
        "VATRate": 0.25,
        "PriceInLocalCurrency": 0.30028609154929575,
        "PriceInLocalCurrencyIncludingVAT": 0.3753576144366197,
        "ExchangeRate": 0.09088,
        "Currency": "SEK"
    },
    {
        "DateTime": "2025-03-21T05:00:00Z",
        "PriceInEUR": 0.034390000000000004,
        "PriceInEURIncludingVAT": 0.042987500000000005,
        "VATRate": 0.25,
        "PriceInLocalCurrency": 0.3784110915492958,
        "PriceInLocalCurrencyIncludingVAT": 0.47301386443661975,
        "ExchangeRate": 0.09088,
        "Currency": "SEK"
    },
    {
        "DateTime": "2025-03-21T06:00:00Z",
        "PriceInEUR": 0.07512,
        "PriceInEURIncludingVAT": 0.09390000000000001,
        "VATRate": 0.25,
        "PriceInLocalCurrency": 0.8265845070422536,
        "PriceInLocalCurrencyIncludingVAT": 1.033230633802817,
        "ExchangeRate": 0.09088,
        "Currency": "SEK"
    },
    {
        "DateTime": "2025-03-21T07:00:00Z",
        "PriceInEUR": 0.036359999999999996,
        "PriceInEURIncludingVAT": 0.04545,
        "VATRate": 0.25,
        "PriceInLocalCurrency": 0.400088028169014,
        "PriceInLocalCurrencyIncludingVAT": 0.5001100352112675,
        "ExchangeRate": 0.09088,
        "Currency": "SEK"
    },
    {
        "DateTime": "2025-03-21T08:00:00Z",
        "PriceInEUR": 0.04335,
        "PriceInEURIncludingVAT": 0.0541875,
        "VATRate": 0.25,
        "PriceInLocalCurrency": 0.4770026408450704,
        "PriceInLocalCurrencyIncludingVAT": 0.596253301056338,
        "ExchangeRate": 0.09088,
        "Currency": "SEK"
    },
    {
        "DateTime": "2025-03-21T09:00:00Z",
        "PriceInEUR": 0.044109999999999996,
        "PriceInEURIncludingVAT": 0.05513749999999999,
        "VATRate": 0.25,
        "PriceInLocalCurrency": 0.4853653169014084,
        "PriceInLocalCurrencyIncludingVAT": 0.6067066461267605,
        "ExchangeRate": 0.09088,
        "Currency": "SEK"
    },
    {
        "DateTime": "2025-03-21T10:00:00Z",
        "PriceInEUR": 0.01067,
        "PriceInEURIncludingVAT": 0.0133375,
        "VATRate": 0.25,
        "PriceInLocalCurrency": 0.11740757042253522,
        "PriceInLocalCurrencyIncludingVAT": 0.146759463028169,
        "ExchangeRate": 0.09088,
        "Currency": "SEK"
    },
    {
        "DateTime": "2025-03-21T11:00:00Z",
        "PriceInEUR": 0.00739,
        "PriceInEURIncludingVAT": 0.0092375,
        "VATRate": 0.25,
        "PriceInLocalCurrency": 0.08131602112676056,
        "PriceInLocalCurrencyIncludingVAT": 0.10164502640845069,
        "ExchangeRate": 0.09088,
        "Currency": "SEK"
    },
    {
        "DateTime": "2025-03-21T12:00:00Z",
        "PriceInEUR": 0.00617,
        "PriceInEURIncludingVAT": 0.007712500000000001,
        "VATRate": 0.25,
        "PriceInLocalCurrency": 0.06789172535211267,
        "PriceInLocalCurrencyIncludingVAT": 0.08486465669014084,
        "ExchangeRate": 0.09088,
        "Currency": "SEK"
    },
    {
        "DateTime": "2025-03-21T13:00:00Z",
        "PriceInEUR": 0.007030000000000001,
        "PriceInEURIncludingVAT": 0.0087875,
        "VATRate": 0.25,
        "PriceInLocalCurrency": 0.07735475352112677,
        "PriceInLocalCurrencyIncludingVAT": 0.09669344190140845,
        "ExchangeRate": 0.09088,
        "Currency": "SEK"
    },
    {
        "DateTime": "2025-03-21T14:00:00Z",
        "PriceInEUR": 0.011359999999999999,
        "PriceInEURIncludingVAT": 0.014199999999999997,
        "VATRate": 0.25,
        "PriceInLocalCurrency": 0.12499999999999999,
        "PriceInLocalCurrencyIncludingVAT": 0.15624999999999997,
        "ExchangeRate": 0.09088,
        "Currency": "SEK"
    },
    {
        "DateTime": "2025-03-21T15:00:00Z",
        "PriceInEUR": 0.01102,
        "PriceInEURIncludingVAT": 0.013775,
        "VATRate": 0.25,
        "PriceInLocalCurrency": 0.1212588028169014,
        "PriceInLocalCurrencyIncludingVAT": 0.15157350352112678,
        "ExchangeRate": 0.09088,
        "Currency": "SEK"
    },
    {
        "DateTime": "2025-03-21T16:00:00Z",
        "PriceInEUR": 0.01537,
        "PriceInEURIncludingVAT": 0.0192125,
        "VATRate": 0.25,
        "PriceInLocalCurrency": 0.16912411971830985,
        "PriceInLocalCurrencyIncludingVAT": 0.2114051496478873,
        "ExchangeRate": 0.09088,
        "Currency": "SEK"
    },
    {
        "DateTime": "2025-03-21T17:00:00Z",
        "PriceInEUR": 0.01852,
        "PriceInEURIncludingVAT": 0.023149999999999997,
        "VATRate": 0.25,
        "PriceInLocalCurrency": 0.2037852112676056,
        "PriceInLocalCurrencyIncludingVAT": 0.254731514084507,
        "ExchangeRate": 0.09088,
        "Currency": "SEK"
    },
    {
        "DateTime": "2025-03-21T18:00:00Z",
        "PriceInEUR": 0.01249,
        "PriceInEURIncludingVAT": 0.0156125,
        "VATRate": 0.25,
        "PriceInLocalCurrency": 0.13743397887323944,
        "PriceInLocalCurrencyIncludingVAT": 0.17179247359154928,
        "ExchangeRate": 0.09088,
        "Currency": "SEK"
    },
    {
        "DateTime": "2025-03-21T19:00:00Z",
        "PriceInEUR": 0.00641,
        "PriceInEURIncludingVAT": 0.0080125,
        "VATRate": 0.25,
        "PriceInLocalCurrency": 0.0705325704225352,
        "PriceInLocalCurrencyIncludingVAT": 0.08816571302816902,
        "ExchangeRate": 0.09088,
        "Currency": "SEK"
    },
    {
        "DateTime": "2025-03-21T20:00:00Z",
        "PriceInEUR": 0.00553,
        "PriceInEURIncludingVAT": 0.0069125,
        "VATRate": 0.25,
        "PriceInLocalCurrency": 0.060849471830985914,
        "PriceInLocalCurrencyIncludingVAT": 0.07606183978873239,
        "ExchangeRate": 0.09088,
        "Currency": "SEK"
    },
    {
        "DateTime": "2025-03-21T21:00:00Z",
        "PriceInEUR": 0.00267,
        "PriceInEURIncludingVAT": 0.0033375,
        "VATRate": 0.25,
        "PriceInLocalCurrency": 0.029379401408450703,
        "PriceInLocalCurrencyIncludingVAT": 0.03672425176056338,
        "ExchangeRate": 0.09088,
        "Currency": "SEK"
    },
    {
        "DateTime": "2025-03-21T22:00:00Z",
        "PriceInEUR": 0.0007099999999999999,
        "PriceInEURIncludingVAT": 0.0008874999999999998,
        "VATRate": 0.25,
        "PriceInLocalCurrency": 0.007812499999999999,
        "PriceInLocalCurrencyIncludingVAT": 0.009765624999999998,
        "ExchangeRate": 0.09088,
        "Currency": "SEK"
    },
    {
        "DateTime": "2025-03-21T23:00:00Z",
        "PriceInEUR": 0.00207,
        "PriceInEURIncludingVAT": 0.0025874999999999995,
        "VATRate": 0.25,
        "PriceInLocalCurrency": 0.022777288732394364,
        "PriceInLocalCurrencyIncludingVAT": 0.02847161091549295,
        "ExchangeRate": 0.09088,
        "Currency": "SEK"
    },
    {
        "DateTime": "2025-03-22T00:00:00Z",
        "PriceInEUR": 0.00058,
        "PriceInEURIncludingVAT": 0.000725,
        "VATRate": 0.25,
        "PriceInLocalCurrency": 0.006382042253521127,
        "PriceInLocalCurrencyIncludingVAT": 0.007977552816901408,
        "ExchangeRate": 0.09088,
        "Currency": "SEK"
    },
    {
        "DateTime": "2025-03-22T01:00:00Z",
        "PriceInEUR": 0.00039,
        "PriceInEURIncludingVAT": 0.0004875,
        "VATRate": 0.25,
        "PriceInLocalCurrency": 0.004291373239436619,
        "PriceInLocalCurrencyIncludingVAT": 0.0053642165492957744,
        "ExchangeRate": 0.09088,
        "Currency": "SEK"
    },
    {
        "DateTime": "2025-03-22T02:00:00Z",
        "PriceInEUR": 0.00035,
        "PriceInEURIncludingVAT": 0.0004375,
        "VATRate": 0.25,
        "PriceInLocalCurrency": 0.0038512323943661973,
        "PriceInLocalCurrencyIncludingVAT": 0.004814040492957746,
        "ExchangeRate": 0.09088,
        "Currency": "SEK"
    },
    {
        "DateTime": "2025-03-22T03:00:00Z",
        "PriceInEUR": 0.00041,
        "PriceInEURIncludingVAT": 0.0005124999999999999,
        "VATRate": 0.25,
        "PriceInLocalCurrency": 0.004511443661971831,
        "PriceInLocalCurrencyIncludingVAT": 0.005639304577464788,
        "ExchangeRate": 0.09088,
        "Currency": "SEK"
    },
    {
        "DateTime": "2025-03-22T04:00:00Z",
        "PriceInEUR": 0.00025,
        "PriceInEURIncludingVAT": 0.0003125,
        "VATRate": 0.25,
        "PriceInLocalCurrency": 0.0027508802816901406,
        "PriceInLocalCurrencyIncludingVAT": 0.0034386003521126762,
        "ExchangeRate": 0.09088,
        "Currency": "SEK"
    },
    {
        "DateTime": "2025-03-22T05:00:00Z",
        "PriceInEUR": 0.00017999999999999998,
        "PriceInEURIncludingVAT": 0.000225,
        "VATRate": 0.25,
        "PriceInLocalCurrency": 0.0019806338028169014,
        "PriceInLocalCurrencyIncludingVAT": 0.0024757922535211265,
        "ExchangeRate": 0.09088,
        "Currency": "SEK"
    },
    {
        "DateTime": "2025-03-22T06:00:00Z",
        "PriceInEUR": -5e-05,
        "PriceInEURIncludingVAT": -5e-05,
        "VATRate": 0.25,
        "PriceInLocalCurrency": -0.0005501760563380282,
        "PriceInLocalCurrencyIncludingVAT": -0.0005501760563380282,
        "ExchangeRate": 0.09088,
        "Currency": "SEK"
    },
    {
        "DateTime": "2025-03-22T07:00:00Z",
        "PriceInEUR": 0.00017999999999999998,
        "PriceInEURIncludingVAT": 0.000225,
        "VATRate": 0.25,
        "PriceInLocalCurrency": 0.0019806338028169014,
        "PriceInLocalCurrencyIncludingVAT": 0.0024757922535211265,
        "ExchangeRate": 0.09088,
        "Currency": "SEK"
    },
    {
        "DateTime": "2025-03-22T08:00:00Z",
        "PriceInEUR": 5.9999999999999995e-05,
        "PriceInEURIncludingVAT": 7.5e-05,
        "VATRate": 0.25,
        "PriceInLocalCurrency": 0.0006602112676056337,
        "PriceInLocalCurrencyIncludingVAT": 0.0008252640845070421,
        "ExchangeRate": 0.09088,
        "Currency": "SEK"
    },
    {
        "DateTime": "2025-03-22T09:00:00Z",
        "PriceInEUR": -0.00022,
        "PriceInEURIncludingVAT": -0.00022,
        "VATRate": 0.25,
        "PriceInLocalCurrency": -0.0024207746478873238,
        "PriceInLocalCurrencyIncludingVAT": -0.0024207746478873238,
        "ExchangeRate": 0.09088,
        "Currency": "SEK"
    },
    {
        "DateTime": "2025-03-22T10:00:00Z",
        "PriceInEUR": -0.00349,
        "PriceInEURIncludingVAT": -0.00349,
        "VATRate": 0.25,
        "PriceInLocalCurrency": -0.03840228873239437,
        "PriceInLocalCurrencyIncludingVAT": -0.03840228873239437,
        "ExchangeRate": 0.09088,
        "Currency": "SEK"
    },
    {
        "DateTime": "2025-03-22T11:00:00Z",
        "PriceInEUR": -0.01002,
        "PriceInEURIncludingVAT": -0.01002,
        "VATRate": 0.25,
        "PriceInLocalCurrency": -0.11025528169014083,
        "PriceInLocalCurrencyIncludingVAT": -0.11025528169014083,
        "ExchangeRate": 0.09088,
        "Currency": "SEK"
    },
    {
        "DateTime": "2025-03-22T12:00:00Z",
        "PriceInEUR": -0.00942,
        "PriceInEURIncludingVAT": -0.00942,
        "VATRate": 0.25,
        "PriceInLocalCurrency": -0.1036531690140845,
        "PriceInLocalCurrencyIncludingVAT": -0.1036531690140845,
        "ExchangeRate": 0.09088,
        "Currency": "SEK"
    },
    {
        "DateTime": "2025-03-22T13:00:00Z",
        "PriceInEUR": -0.00349,
        "PriceInEURIncludingVAT": -0.00349,
        "VATRate": 0.25,
        "PriceInLocalCurrency": -0.03840228873239437,
        "PriceInLocalCurrencyIncludingVAT": -0.03840228873239437,
        "ExchangeRate": 0.09088,
        "Currency": "SEK"
    },
    {
        "DateTime": "2025-03-22T14:00:00Z",
        "PriceInEUR": -0.00016,
        "PriceInEURIncludingVAT": -0.00016,
        "VATRate": 0.25,
        "PriceInLocalCurrency": -0.0017605633802816902,
        "PriceInLocalCurrencyIncludingVAT": -0.0017605633802816902,
        "ExchangeRate": 0.09088,
        "Currency": "SEK"
    },
    {
        "DateTime": "2025-03-22T15:00:00Z",
        "PriceInEUR": 0.0011899999999999999,
        "PriceInEURIncludingVAT": 0.0014874999999999999,
        "VATRate": 0.25,
        "PriceInLocalCurrency": 0.013094190140845069,
        "PriceInLocalCurrencyIncludingVAT": 0.016367737676056336,
        "ExchangeRate": 0.09088,
        "Currency": "SEK"
    },
    {
        "DateTime": "2025-03-22T16:00:00Z",
        "PriceInEUR": 0.0024500000000000004,
        "PriceInEURIncludingVAT": 0.0030625000000000006,
        "VATRate": 0.25,
        "PriceInLocalCurrency": 0.026958626760563383,
        "PriceInLocalCurrencyIncludingVAT": 0.03369828345070423,
        "ExchangeRate": 0.09088,
        "Currency": "SEK"
    },
    {
        "DateTime": "2025-03-22T17:00:00Z",
        "PriceInEUR": 0.00292,
        "PriceInEURIncludingVAT": 0.0036499999999999996,
        "VATRate": 0.25,
        "PriceInLocalCurrency": 0.032130281690140844,
        "PriceInLocalCurrencyIncludingVAT": 0.04016285211267605,
        "ExchangeRate": 0.09088,
        "Currency": "SEK"
    },
    {
        "DateTime": "2025-03-22T18:00:00Z",
        "PriceInEUR": 0.0019299999999999999,
        "PriceInEURIncludingVAT": 0.0024124999999999997,
        "VATRate": 0.25,
        "PriceInLocalCurrency": 0.021236795774647887,
        "PriceInLocalCurrencyIncludingVAT": 0.026545994718309856,
        "ExchangeRate": 0.09088,
        "Currency": "SEK"
    },
    {
        "DateTime": "2025-03-22T19:00:00Z",
        "PriceInEUR": 0.00017,
        "PriceInEURIncludingVAT": 0.00021250000000000002,
        "VATRate": 0.25,
        "PriceInLocalCurrency": 0.0018705985915492959,
        "PriceInLocalCurrencyIncludingVAT": 0.0023382482394366196,
        "ExchangeRate": 0.09088,
        "Currency": "SEK"
    },
    {
        "DateTime": "2025-03-22T20:00:00Z",
        "PriceInEUR": 7.000000000000001e-05,
        "PriceInEURIncludingVAT": 8.750000000000001e-05,
        "VATRate": 0.25,
        "PriceInLocalCurrency": 0.0007702464788732395,
        "PriceInLocalCurrencyIncludingVAT": 0.0009628080985915494,
        "ExchangeRate": 0.09088,
        "Currency": "SEK"
    },
    {
        "DateTime": "2025-03-22T21:00:00Z",
        "PriceInEUR": -0.00015,
        "PriceInEURIncludingVAT": -0.00015,
        "VATRate": 0.25,
        "PriceInLocalCurrency": -0.0016505281690140843,
        "PriceInLocalCurrencyIncludingVAT": -0.0016505281690140843,
        "ExchangeRate": 0.09088,
        "Currency": "SEK"
    },
    {
        "DateTime": "2025-03-22T22:00:00Z",
        "PriceInEUR": -0.00016,
        "PriceInEURIncludingVAT": -0.00016,
        "VATRate": 0.25,
        "PriceInLocalCurrency": -0.0017605633802816902,
        "PriceInLocalCurrencyIncludingVAT": -0.0017605633802816902,
        "ExchangeRate": 0.09088,
        "Currency": "SEK"
    }
]